{
  "parlamentnilisty.cz": {
    "rss_url": "https://www.parlamentnilisty.cz/export/rss.aspx"
  },
  "nwoo.org": {
    "rss_url": "http://www.nwoo.org/feed/"
  },
  "www.zvedavec.org": {
    "rss_url": "http://www.zvedavec.org/zvedavec_rdf_100.xml"
  },
  "www.withform.cz": {
    "use_regex_parser": true,
    "possible_sources": [
      "http://www.withform.cz/page/1/", "http://www.withform.cz/page/2/",
      "http://www.withform.cz/page/3/", "http://www.withform.cz/page/4/",
      "http://www.withform.cz/page/5/", "http://www.withform.cz/page/6/",
      "http://www.withform.cz/page/7/", "http://www.withform.cz/page/8/",
      "http://www.withform.cz/page/9/", "http://www.withform.cz/page/10/",
      "http://www.withform.cz/page/11/", "http://www.withform.cz/page/12/",
      "http://www.withform.cz/page/13/", "http://www.withform.cz/page/14/",
      "http://www.withform.cz/page/15/"
    ],
    "regex": "^http://www\\.withform.cz/(\\d{4})/(\\d{2})/(\\d{2})/[^/]*/$",
    "parse_date": true
  },
  "www.vlasteneckenoviny.cz": {
    "use_regex_parser": true,
    "possible_sources": [
      "http://www.vlasteneckenoviny.cz/?paged=1", "http://www.vlasteneckenoviny.cz/?paged=2",
      "http://www.vlasteneckenoviny.cz/?paged=3", "http://www.vlasteneckenoviny.cz/?paged=4",
      "http://www.vlasteneckenoviny.cz/?paged=5", "http://www.vlasteneckenoviny.cz/?paged=6",
      "http://www.vlasteneckenoviny.cz/?paged=7", "http://www.vlasteneckenoviny.cz/?paged=8",
      "http://www.vlasteneckenoviny.cz/?paged=9", "http://www.vlasteneckenoviny.cz/?paged=10",
      "http://www.vlasteneckenoviny.cz/?paged=11", "http://www.vlasteneckenoviny.cz/?paged=12",
      "http://www.vlasteneckenoviny.cz/?paged=13", "http://www.vlasteneckenoviny.cz/?paged=14",
      "http://www.vlasteneckenoviny.cz/?paged=15", "http://www.vlasteneckenoviny.cz/?paged=16",
      "http://www.vlasteneckenoviny.cz/?paged=17", "http://www.vlasteneckenoviny.cz/?paged=18",
      "http://www.vlasteneckenoviny.cz/?paged=19", "http://www.vlasteneckenoviny.cz/?paged=20",
      "http://www.vlasteneckenoviny.cz/?paged=21", "http://www.vlasteneckenoviny.cz/?paged=22",
      "http://www.vlasteneckenoviny.cz/?paged=23", "http://www.vlasteneckenoviny.cz/?paged=24",
      "http://www.vlasteneckenoviny.cz/?paged=25", "http://www.vlasteneckenoviny.cz/?paged=26",
      "http://www.vlasteneckenoviny.cz/?paged=27", "http://www.vlasteneckenoviny.cz/?paged=28",
      "http://www.vlasteneckenoviny.cz/?paged=29", "http://www.vlasteneckenoviny.cz/?paged=30"
    ],
    "regex": "^http://www\\.vlasteneckenoviny\\.cz/\\?p=\\d+$"
  },
  "www.svetkolemnas.info": {
    "use_regex_parser": true,
    "possible_sources": [
      "http://www.svetkolemnas.info/"
    ],
    "regex": "^/novinky/",
    "domain_prefix": "http://www.svetkolemnas.info/"
  },
  "www.skrytapravda.cz": {
    "rss_url": "http://www.skrytapravda.cz/component/ninjarsssyndicator/?feed_id=1&format=raw"
  },
  "www.securitymagazin.cz": {
    "use_regex_parser": true,
    "possible_sources": [
      "https://www.securitymagazin.cz/?pg=1", "https://www.securitymagazin.cz/?pg=2",
      "https://www.securitymagazin.cz/?pg=3", "https://www.securitymagazin.cz/?pg=4",
      "https://www.securitymagazin.cz/?pg=5", "https://www.securitymagazin.cz/?pg=6",
      "https://www.securitymagazin.cz/?pg=7", "https://www.securitymagazin.cz/?pg=8",
      "https://www.securitymagazin.cz/?pg=9", "https://www.securitymagazin.cz/?pg=10",
      "https://www.securitymagazin.cz/?pg=11", "https://www.securitymagazin.cz/?pg=12",
      "https://www.securitymagazin.cz/?pg=13", "https://www.securitymagazin.cz/?pg=14",
      "https://www.securitymagazin.cz/?pg=15", "https://www.securitymagazin.cz/?pg=16",
      "https://www.securitymagazin.cz/?pg=17", "https://www.securitymagazin.cz/?pg=18",
      "https://www.securitymagazin.cz/?pg=19", "https://www.securitymagazin.cz/?pg=20",
      "https://www.securitymagazin.cz/?pg=21", "https://www.securitymagazin.cz/?pg=22",
      "https://www.securitymagazin.cz/?pg=23", "https://www.securitymagazin.cz/?pg=24",
      "https://www.securitymagazin.cz/?pg=25", "https://www.securitymagazin.cz/?pg=26",
      "https://www.securitymagazin.cz/?pg=27", "https://www.securitymagazin.cz/?pg=28",
      "https://www.securitymagazin.cz/?pg=29", "https://www.securitymagazin.cz/?pg=30"
    ],
    "regex": "^https://www\\.securitymagazin.cz/.*\\.html$"
  },
  "www.rukojmi.cz": {
    "use_regex_parser": true,
    "possible_sources": [
      "http://www.rukojmi.cz/"
    ],
    "regex": "^http://www.rukojmi.cz/clanky/\\d+.*$"
  },
  "www.prvnizpravy.cz": {
    "rss_url": "http://www.prvnizpravy.cz/repository/rss/zpravy_all_cs.xml"
  },
  "www.protiproud.cz": {
    "rss_url": "http://www.protiproud.cz/rss.xml"
  },
  "www.ozonyx.cz": {
    "use_regex_parser": true,
    "possible_sources": [
      "http://www.ozonyx.cz/index.php/page/1/", "http://www.ozonyx.cz/index.php/page/2/",
      "http://www.ozonyx.cz/index.php/page/3/", "http://www.ozonyx.cz/index.php/page/4/",
      "http://www.ozonyx.cz/index.php/page/5/", "http://www.ozonyx.cz/index.php/page/6/",
      "http://www.ozonyx.cz/index.php/page/7/", "http://www.ozonyx.cz/index.php/page/8/",
      "http://www.ozonyx.cz/index.php/page/9/", "http://www.ozonyx.cz/index.php/page/10/",
      "http://www.ozonyx.cz/index.php/page/11/", "http://www.ozonyx.cz/index.php/page/12/",
      "http://www.ozonyx.cz/index.php/page/13/", "http://www.ozonyx.cz/index.php/page/14/",
      "http://www.ozonyx.cz/index.php/page/15/"
    ],
    "regex": "^http://www\\.ozonyx\\.cz/index\\.php/(\\d{4})/(\\d{2})/(\\d{2})/[^/]*/$",
    "parse_date": true
  },
  "www.nejvic-info.cz": {
    "use_regex_parser": true,
    "possible_sources": [
      "https://www.nejvic-info.cz/page/1/", "https://www.nejvic-info.cz/page/2/",
      "https://www.nejvic-info.cz/page/3/", "https://www.nejvic-info.cz/page/4/",
      "https://www.nejvic-info.cz/page/5/", "https://www.nejvic-info.cz/page/6/",
      "https://www.nejvic-info.cz/page/7/", "https://www.nejvic-info.cz/page/8/",
      "https://www.nejvic-info.cz/page/9/", "https://www.nejvic-info.cz/page/10/",
      "https://www.nejvic-info.cz/page/11/", "https://www.nejvic-info.cz/page/12/",
      "https://www.nejvic-info.cz/page/13/", "https://www.nejvic-info.cz/page/14/",
      "https://www.nejvic-info.cz/page/15/"
    ],
    "regex": "^https://www.nejvic-info.cz/[^/]*/$"
  },
  "www.mikan.cz": {
    "rss_url": "https://www.mikan.cz/rss/all.xml"
  },
  "www.lajkit.cz": {
    "use_regex_parser": true,
    "possible_sources": [
      "https://www.lajkit.cz/itemlist?limit=10&start=10", "https://www.lajkit.cz/itemlist?limit=10&start=20",
      "https://www.lajkit.cz/itemlist?limit=10&start=30", "https://www.lajkit.cz/itemlist?limit=10&start=40",
      "https://www.lajkit.cz/itemlist?limit=10&start=50", "https://www.lajkit.cz/itemlist?limit=10&start=60",
      "https://www.lajkit.cz/itemlist?limit=10&start=70", "https://www.lajkit.cz/itemlist?limit=10&start=80",
      "https://www.lajkit.cz/itemlist?limit=10&start=90", "https://www.lajkit.cz/itemlist?limit=10&start=100",
      "https://www.lajkit.cz/itemlist?limit=10&start=110", "https://www.lajkit.cz/itemlist?limit=10&start=120",
      "https://www.lajkit.cz/itemlist?limit=10&start=130", "https://www.lajkit.cz/itemlist?limit=10&start=140",
      "https://www.lajkit.cz/itemlist?limit=10&start=150"
    ],
    "regex": "^/[^/]*/item/[^/]*$",
    "domain_prefix": "https://www.lajkit.cz/"
  },
  "www.krajskelisty.cz": {
    "rss_url": "http://www.krajskelisty.cz/export/rss.xml"
  },
  "www.isstras.eu/cs": {
    "rss_url": "http://www.isstras.eu/cs/feed/"
  },
  "www.halonoviny.cz": {
    "rss_url": "http://www.halonoviny.cz/articles/newsfeed.rss",
    "encoding": "utf-8"
  },
  "www.freepub.cz": {
    "rss_url": "http://www.freepub.cz/feed/"
  },
  "www.freeglobe.cz": {
    "rss_url": "https://www.freeglobe.cz/rss.aspx"
  },
  "www.euserver.cz": {
    "rss_url": "https://www.euserver.cz/rss.aspx"
  },
  "www.euportal.cz": {
    "rss_url": "https://www.euportal.cz/rss.aspx"
  },
  "www.eportal.cz": {
    "rss_url": "https://www.eportal.cz/rss.aspx"
  },
  "www.czechfreepress.cz": {
    "use_regex_parser": true,
    "possible_sources": [
      "http://www.czechfreepress.cz/",
      "http://www.czechfreepress.cz/hlavni-stranka/strana-2.html",
      "http://www.czechfreepress.cz/hlavni-stranka/strana-3.html",
      "http://www.czechfreepress.cz/hlavni-stranka/strana-4.html",
      "http://www.czechfreepress.cz/hlavni-stranka/strana-5.html",
      "http://www.czechfreepress.cz/hlavni-stranka/strana-6.html",
      "http://www.czechfreepress.cz/hlavni-stranka/strana-7.html",
      "http://www.czechfreepress.cz/hlavni-stranka/strana-8.html",
      "http://www.czechfreepress.cz/hlavni-stranka/strana-9.html",
      "http://www.czechfreepress.cz/hlavni-stranka/strana-10.html",
      "http://www.czechfreepress.cz/hlavni-stranka/strana-11.html",
      "http://www.czechfreepress.cz/hlavni-stranka/strana-12.html",
      "http://www.czechfreepress.cz/hlavni-stranka/strana-13.html",
      "http://www.czechfreepress.cz/hlavni-stranka/strana-14.html",
      "http://www.czechfreepress.cz/hlavni-stranka/strana-15.html"
    ],
    "regex": "^/(?!(hlavni)|(profil))[^/]+/[^/]+\\.html$",
    "domain_prefix": "http://www.czechfreepress.cz/"
  },
  "www.ctusi.info": {
    "use_regex_parser": true,
    "possible_sources": [
      "http://www.ctusi.info/",
      "http://www.ctusi.info/?n=1&c=6",
      "http://www.ctusi.info/?n=1&c=15"
    ],
    "regex": "^http://www\\.ctusi\\.info/[^/]+/[^/]+/.*$",
    "encoding": "windows-1250"
  },
  "www.casopis-sifra.cz": {
    "rss_url": "https://www.casopis-sifra.cz/feed/"
  },
  "www.bezpolitickekorektnosti.cz": {
    "rss_url": "http://www.bezpolitickekorektnosti.cz/?feed=rss2"
  },
  "www.alternativnimagazin.cz": {
    "rss_url": "http://www.alternativnimagazin.cz/feed/"
  },
  "wertyzreport.cz": {
    "rss_url": "http://wertyzreport.cz/xml"
  },
  "veksvetla.cz": {
    "rss_url": "http://veksvetla.cz/feed/"
  },
  "tadesco.cz": {
    "rss_url": "https://tadesco.cz/feed/"
  },
  "svobodnenoviny.eu": {
    "use_regex_parser": true,
    "possible_sources": [
      "http://svobodnenoviny.eu/category/z-domova/page/1/",
      "http://svobodnenoviny.eu/category/z-domova/page/2/",
      "http://svobodnenoviny.eu/category/z-domova/page/3/",
      "http://svobodnenoviny.eu/category/ze-sveta/page/1/",
      "http://svobodnenoviny.eu/category/ze-sveta/page/2/",
      "http://svobodnenoviny.eu/category/ze-sveta/page/3/",
      "http://svobodnenoviny.eu/category/uprchlicka-krize/page/1/",
      "http://svobodnenoviny.eu/category/uprchlicka-krize/page/2/",
      "http://svobodnenoviny.eu/category/uprchlicka-krize/page/3/",
      "http://svobodnenoviny.eu/category/zdravi/page/1/",
      "http://svobodnenoviny.eu/category/zdravi/page/2/",
      "http://svobodnenoviny.eu/category/zdravi/page/3/",
      "http://svobodnenoviny.eu/category/zahady-a-exopolitika/page/1/",
      "http://svobodnenoviny.eu/category/zahady-a-exopolitika/page/2/",
      "http://svobodnenoviny.eu/category/zahady-a-exopolitika/page/3/",
      "http://svobodnenoviny.eu/category/konspirace/page/1/",
      "http://svobodnenoviny.eu/category/konspirace/page/2/",
      "http://svobodnenoviny.eu/category/konspirace/page/3/",
      "http://svobodnenoviny.eu/category/duchovno/page/1/",
      "http://svobodnenoviny.eu/category/duchovno/page/2/",
      "http://svobodnenoviny.eu/category/duchovno/page/3/"
    ],
    "regex": "^http://svobodnenoviny\\.eu/[^/]+/$"
  },
  "stredoevropan.cz": {
    "rss_url": "https://stredoevropan.cz/feed/"
  },
  "stalo-se.cz": {
    "rss_url": "https://stalo-se.cz/feed/"
  },
  "proevropu.com": {
    "rss_url": "https://proevropu.com/feed/"
  },
  "procproto.cz": {
    "rss_url": "http://procproto.cz/feed/"
  },
  "pravyprostor.cz": {
    "rss_url": "https://pravyprostor.cz/feed/"
  },
  "pravdive.eu": {
    "rss_url": "http://pravdive.eu/rss.xml",
    "encoding": "utf-8"
  },
  "outsidermedia.cz": {
    "rss_url": "http://outsidermedia.cz/feed/"
  },
  "orgo-net.blogspot.com": {
    "rss_url": "http://orgo-net.blogspot.com/feeds/posts/default?alt=rss"
  },
  "news.e-republika.cz": {
    "rss_url": "https://e-republika.cz/tiki-articles_rss.php?ver=2"
  },
  "morezprav.cz": {
    "use_regex_parser": true,
    "possible_sources": [
      "https://morezprav.cz/category/mix/page/1/",
      "https://morezprav.cz/category/mix/page/2/",
      "https://morezprav.cz/category/mix/page/3/",
      "https://morezprav.cz/category/konspirace/page/1/",
      "https://morezprav.cz/category/konspirace/page/2/",
      "https://morezprav.cz/category/konspirace/page/3/",
      "https://morezprav.cz/category/vesmir/page/1/",
      "https://morezprav.cz/category/vesmir/page/2/",
      "https://morezprav.cz/category/vesmir/page/3/",
      "https://morezprav.cz/category/svetodeni/page/1/",
      "https://morezprav.cz/category/svetodeni/page/2/",
      "https://morezprav.cz/category/svetodeni/page/3/",
      "https://morezprav.cz/category/zdravi/page/1/",
      "https://morezprav.cz/category/zdravi/page/2/",
      "https://morezprav.cz/category/zdravi/page/3/",
      "https://morezprav.cz/category/cestovani/page/1/",
      "https://morezprav.cz/category/cestovani/page/2/",
      "https://morezprav.cz/category/cestovani/page/3/"
    ],
    "regex": "^https://morezprav\\.cz/[^/]+/[^/]+$"
  },
  "megazine.cz": {
    "rss_url": "http://megazine.cz/feed/"
  },
  "jackings.net": {
    "rss_url": "https://jackings.net/feed/"
  },
  "ipribeh.cz": {
    "use_regex_parser": true,
    "possible_sources": [
      "http://ipribeh.cz/page/1/",
      "http://ipribeh.cz/page/2/",
      "http://ipribeh.cz/page/3/",
      "http://ipribeh.cz/page/4/",
      "http://ipribeh.cz/page/5/",
      "http://ipribeh.cz/page/6/",
      "http://ipribeh.cz/page/7/",
      "http://ipribeh.cz/page/8/",
      "http://ipribeh.cz/page/9/",
      "http://ipribeh.cz/page/10/"
    ],
    "regex": "^http://ipribeh\\.cz/([^/-]+-){5}[^/]+/$"
  },
  "instory.cz": {
    "rss_url": "https://instory.cz/rss/"
  },
  "farmazdravi.cz": {
    "rss_url": "https://farmazdravi.cz/feed/"
  },
  "www.eurasia24.cz": {
    "rss_url": "https://www.eurasia24.cz/clanky-eurasia24/itemlist?format=feed&moduleID=614"
  },
  "cz.sputniknews.com": {
    "rss_url": "https://cz.sputniknews.com/export/rss2/archive/index.xml"
  },
  "ceskozdrave.cz": {
    "rss_url": "https://ceskozdrave.cz/feed/"
  },
  "ceskoaktualne.cz": {
    "rss_url": "https://ceskoaktualne.cz/feed/"
  },
  "aeronet.cz": {
    "rss_url": "https://aeronet.cz/news/feed/"
  },
  "ac24.cz": {
    "rss_url": "https://ac24.cz/rss/feed.xml"
  },
  "www.duchdoby.cz": {
    "rss_url": "https://www.duchdoby.cz/feed/"
  },
  "zpravy.dt24.cz": {
    "rss_url": "https://zpravy.dt24.cz/feed/"
  },
  "e-republika.cz": {
    "rss_url": "http://e-republika.cz/tiki-articles_rss.php?ver=2"
  },
  "www.eurabia.cz": {
    "rss_url": "https://www.eurabia.cz/rss.aspx"
  },
  "eurodenik.cz": {
    "rss_url": "http://eurodenik.cz/feed"
  },
  "eurozpravy.cz": {
    "rss_url": "https://eurozpravy.cz/rss/all/"
  },
  "leva-net.webnode.cz": {
    "rss_url": "http://leva-net.webnode.cz/rss/all.xml"
  },
  "www.necenzurujeme.cz": {
    "rss_url": "http://www.necenzurujeme.cz/feed/rss.php"
  },
  "www.novaburzoazie.com": {
    "rss_url": "http://www.novaburzoazie.com/436356161/feed.rss"
  },
  "vasevec.parlamentnilisty.cz": {
    "rss_url": "http://vasevec.parlamentnilisty.cz/rss.xml"
  },
  "idnes.cz": {
    "rss_url": "https://servis.idnes.cz/rss.aspx",
    "encoding": "windows-1250"
  },
  "novinky.cz": {
    "rss_url": "https://www.novinky.cz/rss2/"
  },
  "irozhlas.cz": {
    "rss_url": "https://www.irozhlas.cz/rss/irozhlas"
  }
}